{
    "dependencies": [
        {
            "name": "kube-prometheus",
            "source": {
                "git": {
                    "remote": "https://github.com/coreos/kube-prometheus",
                    "subdir": "jsonnet/kube-prometheus"
                }
            },
            "version": "5e1758c45380093f412c751aa6781ca88f02b59e"
        },
        {
            "name": "ksonnet",
            "source": {
                "git": {
                    "remote": "https://github.com/ksonnet/ksonnet-lib",
                    "subdir": ""
                }
            },
            "version": "0d2f82676817bbf9e4acf6495b2090205f323b9f"
        },
        {
            "name": "kubernetes-mixin",
            "source": {
                "git": {
                    "remote": "https://github.com/kubernetes-monitoring/kubernetes-mixin",
                    "subdir": ""
                }
            },
            "version": "cd0cd56feeb92bee42c31a4649984137b3f25a3d"
        },
        {
            "name": "grafonnet",
            "source": {
                "git": {
                    "remote": "https://github.com/grafana/grafonnet-lib",
                    "subdir": "grafonnet"
                }
            },
            "version": "69bc267211790a1c3f4ea6e6211f3e8ffe22f987"
        },
        {
            "name": "grafana-builder",
            "source": {
                "git": {
                    "remote": "https://github.com/kausalco/public",
                    "subdir": "grafana-builder"
                }
            },
            "version": "2b9b14d0d91adf8781e5b2c9b62dc8cb180a9886"
        },
        {
            "name": "grafana",
            "source": {
                "git": {
                    "remote": "https://github.com/brancz/kubernetes-grafana",
                    "subdir": "grafana"
                }
            },
            "version": "c79fdb1f6cbd14a003f73d9a6f571f1cefc6638d"
        },
        {
            "name": "prometheus-operator",
            "source": {
                "git": {
                    "remote": "https://github.com/coreos/prometheus-operator",
                    "subdir": "jsonnet/prometheus-operator"
                }
            },
            "version": "18fbf558ab7f8809fd610a3dc50bf483508dc1bb"
        },
        {
            "name": "etcd-mixin",
            "source": {
                "git": {
                    "remote": "https://github.com/coreos/etcd",
                    "subdir": "Documentation/etcd-mixin"
                }
            },
            "version": "555eb1951f2ea5fb79b2bcd21e4b7cccef2a5562"
        }
    ]
}
